pip_viz/__init__.py
pip_viz/pip_viz.py
pip_viz-0.0.7.dist-info/METADATA
pip_viz-0.0.7.dist-info/WHEEL
pip_viz-0.0.7.dist-info/entry_points.txt
pip_viz-0.0.7.dist-info/licenses/LICENSE
pip_viz-0.0.7.dist-info/RECORD
