Metadata-Version: 2.4
Name: pip-viz
Version: 0.0.7
Summary: A package that generates a graph of dependencies using Graphviz
Project-URL: Homepage, https://github.com/jocassid/pip-viz
Project-URL: Documentation, https://github.com/jocassid/pip-viz/blob/main/README.md
Project-URL: Repository, https://github.com/jocassid/pip-viz.git
Project-URL: Issues, https://github.com/jocassid/pip-viz/issues
Project-URL: Changelog, https://github.com/jocassid/pip-viz/blob/main/README.md
Author-email: John Cassidy <jocassid@gmail.com>
Maintainer-email: John Cassidy <jocassid@gmail.com>
License: MIT License
License-File: LICENSE
Keywords: dependencies,graph,graphviz,pip
Classifier: License :: OSI Approved :: MIT License
Classifier: Operating System :: OS Independent
Classifier: Programming Language :: Python :: 3
Requires-Python: >=3.8
Requires-Dist: graphviz>=0.20.2
